projects_tools/__init__.py
projects_tools/commands.py
projects_tools/mcp_server_projects_tools.py
projects_tools/react_tasks.py
projects_tools/utils.py
projects_tools/version.py
projects_tools/vue_tasks.py
projects_tools/templates/Makefile.jinja2
projects_tools/templates/README.md.jinja2
projects_tools/templates/deploy.sh.jinja2
projects_tools/templates/proxy.py.jinja2
projects_tools/templates/setup.py.jinja2
projects_tools-0.0.4.dist-info/METADATA
projects_tools-0.0.4.dist-info/WHEEL
projects_tools-0.0.4.dist-info/entry_points.txt
projects_tools-0.0.4.dist-info/top_level.txt
projects_tools-0.0.4.dist-info/RECORD
