Metadata-Version: 2.1
Name: projects_tools
Version: 0.0.4
Summary: Projects Tools: A tool for managing projects
Author: allwefantasy
Classifier: Topic :: Scientific/Engineering :: Artificial Intelligence
Classifier: Programming Language :: Python :: 3.9
Classifier: Programming Language :: Python :: 3.10
Classifier: Programming Language :: Python :: 3.11
Requires-Dist: jinja2
Requires-Dist: click
Requires-Dist: rich
